LICENSE
README.md
setup.cfg
setup.py
g3x.egg-info/PKG-INFO
g3x.egg-info/SOURCES.txt
g3x.egg-info/dependency_links.txt
g3x.egg-info/top_level.txt
galax/__init__.py
galax/_version.py
galax/core.py
galax/function.py
galax/graph_index.py
galax/heterograph.py
galax/heterograph_index.py
galax/view.py
galax/data/__init__.py
galax/nn/__init__.py
galax/nn/module.py
galax/nn/utils.py
galax/nn/zoo/__init__.py
galax/nn/zoo/gcn.py