Metadata-Version: 2.1
Name: g3x
Version: 0.0
Author: Yuanqing Wang
Author-email: wangyq@wangyq.net
License: MIT
License-File: LICENSE
